dtscore/__init__.py
dtscore/consoleutils.py
dtscore/csvnames.py
dtscore/dataframenames.py
dtscore/domain.py
dtscore/events.py
dtscore/fileutils.py
dtscore/globals.py
dtscore/logging.py
dtscore/queuemanager.py
dtscore/schema_enums.py
dtscore/tiingo.py
dtscore/tws.py
dtscore/utils.py
dtscore/ibapi/__init__.py
dtscore/ibapi/account_summary_tags.py
dtscore/ibapi/client.py
dtscore/ibapi/comm.py
dtscore/ibapi/commission_report.py
dtscore/ibapi/common.py
dtscore/ibapi/connection.py
dtscore/ibapi/const.py
dtscore/ibapi/contract.py
dtscore/ibapi/decoder.py
dtscore/ibapi/enum_implem.py
dtscore/ibapi/errors.py
dtscore/ibapi/execution.py
dtscore/ibapi/ineligibility_reason.py
dtscore/ibapi/message.py
dtscore/ibapi/news.py
dtscore/ibapi/object_implem.py
dtscore/ibapi/order.py
dtscore/ibapi/order_cancel.py
dtscore/ibapi/order_condition.py
dtscore/ibapi/order_state.py
dtscore/ibapi/orderdecoder.py
dtscore/ibapi/reader.py
dtscore/ibapi/scanner.py
dtscore/ibapi/server_versions.py
dtscore/ibapi/softdollartier.py
dtscore/ibapi/tag_value.py
dtscore/ibapi/ticktype.py
dtscore/ibapi/utils.py
dtscore/ibapi/wrapper.py
dtscore-2.4.0.dist-info/licenses/LICENSE
dtscore-2.4.0.dist-info/METADATA
dtscore-2.4.0.dist-info/WHEEL
dtscore-2.4.0.dist-info/top_level.txt
dtscore-2.4.0.dist-info/RECORD
