Metadata-Version: 2.4
Name: dtscore
Version: 2.4.0
Summary: DTS Core Services
Author-email: "D. Smith" <dgsmith.hpot@gmail.com>
Classifier: Development Status :: 5 - Production/Stable
Classifier: Environment :: Console
Classifier: Intended Audience :: Developers
Classifier: License :: OSI Approved :: BSD License
Classifier: Operating System :: Microsoft :: Windows :: Windows 11
Classifier: Programming Language :: Python :: 3.10
Requires-Python: >=3.10
License-File: LICENSE
Requires-Dist: importlib-metadata; python_version >= "3.10"
Requires-Dist: requests>=2.31
Requires-Dist: urllib3>=2.0
Dynamic: license-file
